b1ddi/__init__.py
b1ddi/bin/__init__.py
b1ddi/bin/b1ddi-dhcp-config-profile.py
b1ddi/bin/b1ddi-dhcp-ddns.py
b1ddi/bin/b1ddi-dhcp-fixedaddress.py
b1ddi/bin/b1ddi-dhcp-ha.py
b1ddi/bin/b1ddi-dhcp-ipspace.py
b1ddi/bin/b1ddi-dhcp-network-name.py
b1ddi/bin/b1ddi-dhcp-network-service-instance.py
b1ddi/bin/b1ddi-dhcp-option-filters.py
b1ddi/bin/b1ddi-dhcp-options.py
b1ddi/bin/b1ddi-dhcp-profile.py
b1ddi/bin/b1ddi-dns-authzone.py
b1ddi/bin/b1ddi-dns-namedacl.py
b1ddi/bin/b1ddi-dns-nsg.py
b1ddi/bin/b1ddi-dns-profile.py
b1ddi/bin/b1ddi-dns-record.py
b1ddi/bin/b1ddi-dns-recordlookup.py
b1ddi/bin/b1ddi-dns-view.py
b1ddi/bin/b1ddi-framework.py
b1ddi/bin/b1ddi-users.py
b1ddi/bin/b1infra-host-services.py
b1ddi/bin/b1td-named-lists.py
b1ddi/bin/b1ztp-join-token.py
b1ddi-0.0.3.dist-info/METADATA
b1ddi-0.0.3.dist-info/WHEEL
b1ddi-0.0.3.dist-info/entry_points.txt
b1ddi-0.0.3.dist-info/licenses/LICENSE.txt
b1ddi-0.0.3.dist-info/RECORD
